funkyheatmappy/__about__.py
funkyheatmappy/__init__.py
funkyheatmappy/add_column_if_missing.py
funkyheatmappy/calculate_column_positions.py
funkyheatmappy/calculate_positions.py
funkyheatmappy/calculate_row_positions.py
funkyheatmappy/compose_plot.py
funkyheatmappy/create_legends.py
funkyheatmappy/funkyheatmappy.py
funkyheatmappy/make_data_processor.py
funkyheatmappy/position_arguments.py
funkyheatmappy/score_to_funkyrectangle.py
funkyheatmappy/verify_column_groups.py
funkyheatmappy/verify_column_info.py
funkyheatmappy/verify_data.py
funkyheatmappy/verify_legends.py
funkyheatmappy/verify_palettes.py
funkyheatmappy/verify_row_groups.py
funkyheatmappy/verify_row_info.py
funkyheatmappy-0.7.0.dist-info/METADATA
funkyheatmappy-0.7.0.dist-info/WHEEL
funkyheatmappy-0.7.0.dist-info/licenses/LICENSE
funkyheatmappy-0.7.0.dist-info/RECORD
