Metadata-Version: 2.3
Name: funkyheatmappy
Version: 0.7.0
Summary: Generate heatmap-like visualisations for benchmark data frames.
Project-URL: documentation, https://funkyheatmap.github.io/funkyheatmappy/
Project-URL: Homepage, https://github.com/funkyheatmap/funkyheatmappy
Project-URL: Source, https://github.com/funkyheatmap/funkyheatmappy
Author-email: Louise Deconinck <louise.deconinck@gmail.com>, Artuur Couckuyt <artuur_couckuyt@hotmail.com>
Maintainer-email: Louise Deconinck <louise.deconinck@gmail.com>, Artuur Couckuyt <artuur_couckuyt@hotmail.com>
License: The MIT License (MIT)
Classifier: Programming Language :: Python :: 3 :: Only
Classifier: Programming Language :: Python :: 3.10
Classifier: Programming Language :: Python :: 3.11
Classifier: Programming Language :: Python :: 3.12
Requires-Python: >=3.10
Requires-Dist: matplotlib
Requires-Dist: numpy
Requires-Dist: pandas
Provides-Extra: doc
Requires-Dist: sphinx; extra == 'doc'
Requires-Dist: sphinx-autoapi; extra == 'doc'
Provides-Extra: test
Requires-Dist: pytest; extra == 'test'
